{
  "indexes": [
    {
      "collectionGroup": "gameInvites",
      "queryScope": "COLLECTION",
      "fields": [
        {"fieldPath": "from", "order": "ASCENDING"},
        {"fieldPath": "to", "order": "ASCENDING"}
      ]
    },
    {
      "collectionGroup": "gameSessions",
      "queryScope": "COLLECTION",
      "fields": [
        {"fieldPath": "players", "arrayConfig": "CONTAINS"},
        {"fieldPath": "createdAt", "order": "DESCENDING"}
      ]
    }
    ,
    {
      "collectionGroup": "users",
      "queryScope": "COLLECTION",
      "fields": [
        {"fieldPath": "location", "order": "ASCENDING"},
        {"fieldPath": "uid", "order": "ASCENDING"}
      ]
    }
  ],
  "fieldOverrides": []
}
